django_mediastorage/__init__.py
django_mediastorage/_version.py
django_mediastorage/apps.py
django_mediastorage/checks.py
django_mediastorage/constants.py
django_mediastorage/fields.py
django_mediastorage/models.py
django_mediastorage/response.py
django_mediastorage/settings.py
django_mediastorage/urls.py
django_mediastorage/management/__init__.py
django_mediastorage/management/commands/__init__.py
django_mediastorage/management/commands/list_filestorage_directories.py
django_mediastorage/management/commands/list_filestorage_unknown_files.py
django_mediastorage/migrations/__init__.py
django_mediastorage/storage/__init__.py
django_mediastorage/storage/fields.py
django_mediastorage/storage/inventory.py
django_mediastorage/storage/storage.py
django_mediastorage/views/__init__.py
django_mediastorage/views/files.py
django_mediastorage/views/generator.py
django_mediastorage/views/http_forward_auth.py
django_mediastorage-0.1.0.dist-info/licenses/LICENSE
django_mediastorage-0.1.0.dist-info/METADATA
django_mediastorage-0.1.0.dist-info/WHEEL
django_mediastorage-0.1.0.dist-info/top_level.txt
django_mediastorage-0.1.0.dist-info/RECORD
