Metadata-Version: 2.4
Name: django-mediastorage
Version: 0.1.0
Summary: A library that allows to protect media files that are served via nginx or traefik to be authenticated
Author-email: Jonas und der Wolf GmbH <opensource@jonasundderwolf.de>, Alissa Gerhard <alissa.gerhard@jonasundderwolf.de>
License-Expression: LGPL-2.1-or-later
Keywords: django,mediastorage
Classifier: Development Status :: 3 - Alpha
Classifier: Environment :: Web Environment
Classifier: Framework :: Django
Classifier: Intended Audience :: Developers
Classifier: Programming Language :: Python
Classifier: Programming Language :: Python :: 3
Classifier: Programming Language :: Python :: 3.12
Classifier: Programming Language :: Python :: 3.13
Classifier: Operating System :: OS Independent
Classifier: Framework :: Django :: 4.2
Classifier: Framework :: Django :: 5
Classifier: Framework :: Django :: 5.0
Classifier: Framework :: Django :: 5.1
Classifier: Framework :: Django :: 5.2
Classifier: Topic :: Software Development :: Libraries :: Python Modules
Requires-Python: >=3.12
License-File: LICENSE
Requires-Dist: django>=4.2
Requires-Dist: djangorestframework>=3.15
Dynamic: license-file
